hashdb_cli/__init__.py
hashdb_cli-0.1.2.dist-info/entry_points.txt
hashdb_cli-0.1.2.dist-info/LICENSE
hashdb_cli-0.1.2.dist-info/WHEEL
hashdb_cli-0.1.2.dist-info/METADATA
hashdb_cli-0.1.2.dist-info/RECORD
