Metadata-Version: 2.1
Name: hashdb-cli
Version: 0.1.2
Summary: Access the open analysis hashdb via cli
Home-page: https://github.com/3c7/hashdb-cli
License: MIT
Author: 3c7
Author-email: 3c7@posteo.de
Requires-Python: >=3.10,<4.0
Classifier: License :: OSI Approved :: MIT License
Classifier: Operating System :: OS Independent
Classifier: Programming Language :: Python :: 3
Classifier: Programming Language :: Python :: 3.10
Requires-Dist: requests (>=2.28.1,<3.0.0)
Requires-Dist: typer (>=0.6.1,<0.7.0)
Project-URL: Repository, https://github.com/3c7/hashdb-cli
